qmaterialwidgets/__init__.py
qmaterialwidgets/_rc/__init__.py
qmaterialwidgets/_rc/resource.py
qmaterialwidgets/common/__init__.py
qmaterialwidgets/common/animation.py
qmaterialwidgets/common/auto_wrap.py
qmaterialwidgets/common/color.py
qmaterialwidgets/common/config.py
qmaterialwidgets/common/exception_handler.py
qmaterialwidgets/common/font.py
qmaterialwidgets/common/icon.py
qmaterialwidgets/common/overload.py
qmaterialwidgets/common/router.py
qmaterialwidgets/common/smooth_scroll.py
qmaterialwidgets/common/style_sheet.py
qmaterialwidgets/common/translator.py
qmaterialwidgets/common/material_color/__init__.py
qmaterialwidgets/common/material_color/blend/__init__.py
qmaterialwidgets/common/material_color/blend/blend.py
qmaterialwidgets/common/material_color/hct/__init__.py
qmaterialwidgets/common/material_color/hct/cam16.py
qmaterialwidgets/common/material_color/hct/hct.py
qmaterialwidgets/common/material_color/hct/viewing_conditions.py
qmaterialwidgets/common/material_color/palettes/__init__.py
qmaterialwidgets/common/material_color/palettes/core_palette.py
qmaterialwidgets/common/material_color/palettes/tonal_palette.py
qmaterialwidgets/common/material_color/quantize/__init__.py
qmaterialwidgets/common/material_color/quantize/lab_point_provider.py
qmaterialwidgets/common/material_color/quantize/quantizer_celebi.py
qmaterialwidgets/common/material_color/quantize/quantizer_map.py
qmaterialwidgets/common/material_color/quantize/quantizer_wsmeans.py
qmaterialwidgets/common/material_color/quantize/quantizer_wu.py
qmaterialwidgets/common/material_color/scheme/__init__.py
qmaterialwidgets/common/material_color/scheme/scheme.py
qmaterialwidgets/common/material_color/score/__init__.py
qmaterialwidgets/common/material_color/score/score.py
qmaterialwidgets/common/material_color/utils/__init__.py
qmaterialwidgets/common/material_color/utils/color_utils.py
qmaterialwidgets/common/material_color/utils/image_utils.py
qmaterialwidgets/common/material_color/utils/math_utils.py
PySide2_Material_Widgets-0.9.10.dist-info/LICENSE
PySide2_Material_Widgets-0.9.10.dist-info/METADATA
PySide2_Material_Widgets-0.9.10.dist-info/WHEEL
PySide2_Material_Widgets-0.9.10.dist-info/top_level.txt
PySide2_Material_Widgets-0.9.10.dist-info/RECORD
