Metadata-Version: 2.1
Name: PySide2-Material-Widgets
Version: 0.9.10
Summary: A material design widgets library based on PySide2
Home-page: https://github.com/zhiyiYo/QMaterialWidgets/tree/PySide2
Author: zhiyiYo
Author-email: shokokawaii@outlook.com
License: GPLv3
Project-URL: Documentation, https://qmaterialwidgets.readthedocs.io/
Project-URL: Source Code, https://github.com/zhiyiYo/QMaterialWidgets/tree/PySide2
Project-URL: Bug Tracker, https://github.com/zhiyiYo/QMaterialWidgets/issues
Keywords: pyside2 material widgets
Platform: UNKNOWN
Classifier: Programming Language :: Python :: 3
Classifier: License :: OSI Approved :: GNU General Public License v3 (GPLv3)
Classifier: Operating System :: OS Independent
License-File: LICENSE
Requires-Dist: PySide2 (>=5.15.0)
Requires-Dist: PySide2-Frameless-Window
Requires-Dist: darkdetect
